otpauth/__init__.py
otpauth/_rfc4226.py
otpauth/_rfc6238.py
otpauth/core.py
otpauth/py.typed
otpauth-2.2.0.dist-info/METADATA
otpauth-2.2.0.dist-info/WHEEL
otpauth-2.2.0.dist-info/licenses/LICENSE
otpauth-2.2.0.dist-info/RECORD
