Metadata-Version: 2.4
Name: otpauth
Version: 2.2.0
Summary: Implements one time password of HOTP/TOTP
Project-URL: Source, https://github.com/authlib/otpauth
Project-URL: Documentation, https://otp.authlib.org/
Project-URL: Donate, https://github.com/sponsors/authlib
Project-URL: Blog, https://blog.authlib.org/
Author-email: Hsiaoming Yang <me@lepture.com>
License: BSD-3-Clause
License-File: LICENSE
Classifier: Development Status :: 5 - Production/Stable
Classifier: Environment :: Console
Classifier: Environment :: Web Environment
Classifier: Intended Audience :: Developers
Classifier: License :: OSI Approved :: BSD License
Classifier: Operating System :: OS Independent
Classifier: Programming Language :: Python
Classifier: Programming Language :: Python :: 3
Classifier: Programming Language :: Python :: 3.7
Classifier: Programming Language :: Python :: 3.8
Classifier: Programming Language :: Python :: 3.9
Classifier: Programming Language :: Python :: 3.10
Classifier: Programming Language :: Python :: 3.11
Classifier: Programming Language :: Python :: 3.12
Classifier: Programming Language :: Python :: 3.13
Classifier: Programming Language :: Python :: Implementation :: CPython
Classifier: Programming Language :: Python :: Implementation :: PyPy
Classifier: Topic :: Security
Classifier: Topic :: Utilities
Requires-Python: >=3.7
